tests/__init__.py
tests/data_generation.py
tests/test_detectors.py
tests/test_mvdetectors.py
tests/test_persistence.py
tsod/__init__.py
tsod/autoencoder_lstm.py
tsod/autoencoders.py
tsod/base.py
tsod/custom_exceptions.py
tsod/detectors.py
tsod/features.py
tsod/hampel.py
tsod/mvdetectors.py
tsod/active_learning/__init__.py
tsod/active_learning/app.py
tsod/active_learning/components.py
tsod/active_learning/data_structures.py
tsod/active_learning/instructions.py
tsod/active_learning/modelling.py
tsod/active_learning/plotting.py
tsod/active_learning/test.py
tsod/active_learning/upload_data.py
tsod/active_learning/utils.py
tsod-0.2.0.dist-info/LICENSE
tsod-0.2.0.dist-info/METADATA
tsod-0.2.0.dist-info/WHEEL
tsod-0.2.0.dist-info/top_level.txt
tsod-0.2.0.dist-info/RECORD
