Metadata-Version: 2.1
Name: tsod
Version: 0.2.0
Summary: Time series anomaly detection.
Home-page: https://github.com/DHI/tsod
Author: Henrik Andersson
Author-email: jan@dhigroup.com
License: MIT
Classifier: License :: OSI Approved :: MIT License
Classifier: Development Status :: 2 - Pre-Alpha
Classifier: Intended Audience :: Science/Research
Classifier: Programming Language :: Python
Classifier: Programming Language :: Python :: 3
Classifier: Programming Language :: Python :: 3.8
Classifier: Programming Language :: Python :: 3.9
Classifier: Programming Language :: Python :: 3.10
Classifier: Programming Language :: Python :: 3.11
Classifier: Operating System :: OS Independent
Classifier: Topic :: Scientific/Engineering
License-File: LICENSE
Requires-Dist: pandas >=1.0.0
Requires-Dist: numba
Requires-Dist: joblib
Provides-Extra: dev
Requires-Dist: pytest >=6.2.1 ; extra == 'dev'
Requires-Dist: sphinx ==4.5.0 ; extra == 'dev'
Requires-Dist: sphinx-book-theme ; extra == 'dev'
Provides-Extra: ml
Requires-Dist: pyod ; extra == 'ml'
Requires-Dist: tensorflow ; extra == 'ml'
Provides-Extra: test
Requires-Dist: pytest >=6.2.1 ; extra == 'test'
